AUTHORS
LICENSE
MANIFEST.in
README.rst
setup.py
chameleon/__init__.py
chameleon/__init__.pyc
chameleon/context_processors.py
chameleon/context_processors.pyc
chameleon/models.py
chameleon/models.pyc
chameleon/tests.py
chameleon/views.py
chameleon/conf/app_template/README.md
chameleon/conf/app_template/__init__.py
chameleon/conf/app_template/__init__.pyc
chameleon/conf/app_template/settings.py
chameleon/conf/app_template/setup.py
chameleon/conf/app_template/static/app_name/css/constants.less
chameleon/conf/app_template/static/app_name/css/edit.css
chameleon/conf/app_template/static/app_name/css/elements.less
chameleon/conf/app_template/static/app_name/css/fluidable.less
chameleon/conf/app_template/static/app_name/css/fonts.less
chameleon/conf/app_template/static/app_name/css/menu.less
chameleon/conf/app_template/static/app_name/css/mixins.less
chameleon/conf/app_template/static/app_name/css/normalize.css
chameleon/conf/app_template/static/app_name/css/ottermixins.less
chameleon/conf/app_template/static/app_name/css/style.less
chameleon/conf/app_template/static/app_name/js/css3-mediaqueries.js
chameleon/conf/app_template/static/app_name/js/jquery.min.js
chameleon/conf/app_template/static/app_name/js/less-1.3.3.min.js
chameleon/conf/app_template/static/app_name/js/modernizr.js
chameleon/conf/app_template/templates/app_name/app_name.html
chameleon/conf/app_template/templates/app_name/sample.html
chameleon/management/__init__.py
chameleon/management/__init__.pyc
chameleon/management/commands/__init__.py
chameleon/management/commands/__init__.pyc
chameleon/management/commands/lessc.pyc
chameleon/management/commands/purifyhtml.py
chameleon/management/commands/purifyhtml.pyc
chameleon/management/commands/starttheme.py
chameleon/management/commands/starttheme.pyc
chameleon/templatetags/__init__.py
chameleon/templatetags/__init__.pyc
chameleon/templatetags/chameleon.py
chameleon/templatetags/chameleon.pyc
django_chameleon.egg-info/PKG-INFO
django_chameleon.egg-info/SOURCES.txt
django_chameleon.egg-info/dependency_links.txt
django_chameleon.egg-info/entry_points.txt
django_chameleon.egg-info/not-zip-safe
django_chameleon.egg-info/requires.txt
django_chameleon.egg-info/top_level.txt