Metadata-Version: 1.1
Name: django-chameleon
Version: 0.0.2a1
Summary: A Django app that will create a pluggable django-cms theme app within your project.
Home-page: https://bitbucket.org/oddotterco/django-chameleon
Author: Odd Otter Co
Author-email: chameleon@oddotter.com
License: BSD
Keywords: django,cms,theme
Platform: Linux
Classifier: Development Status :: 2 - Pre-Alpha
Classifier: Framework :: Django
Classifier: Intended Audience :: Developers
Classifier: License :: OSI Approved :: BSD License
Classifier: Operating System :: OS Independent
Classifier: Programming Language :: Python
Classifier: Topic :: Internet :: WWW/HTTP
Classifier: Topic :: Internet :: WWW/HTTP :: Dynamic Content
